python4_90_poetry_2/__init__.py
python4_90_poetry_2/app.py
python4_90_poetry_2/model/__init__.py
python4_90_poetry_2/model/person.py
python4_90_poetry_2-0.1.0.dist-info/WHEEL
python4_90_poetry_2-0.1.0.dist-info/METADATA
python4_90_poetry_2-0.1.0.dist-info/RECORD
