Metadata-Version: 2.1
Name: python4-90-poetry-2
Version: 0.1.0
Summary: 
Author: Krzysztof
Author-email: programowanie.krzysiek@gmail.com
Requires-Python: >=3.11,<4.0
Classifier: Programming Language :: Python :: 3
Classifier: Programming Language :: Python :: 3.11
Requires-Dist: django (>=4.1,<5.0)
Requires-Dist: pendulum (>=2.1.2,<3.0.0)
